reader/__init__.py
reader/__main__.py
reader/config.txt
reader/feed.py
reader/viewer.py
praneet_reader-1.1.0.dist-info/METADATA
praneet_reader-1.1.0.dist-info/WHEEL
praneet_reader-1.1.0.dist-info/entry_points.txt
praneet_reader-1.1.0.dist-info/top_level.txt
praneet_reader-1.1.0.dist-info/RECORD
