Metadata-Version: 2.1
Name: praneet-reader
Version: 1.1.0
Summary: Real the latest Real Python tutorials
Home-page: https://github.com/Praneet460
Author: Praneet Nigam
Author-email: nigampraneet460@gmail.com
License: MIT
Platform: UNKNOWN
Classifier: License :: OSI Approved :: MIT License
Classifier: Programming Language :: Python :: 3
Classifier: Programming Language :: Python :: 3.7
Requires-Dist: feedparser
Requires-Dist: html2text
